pordego_dependency/__init__.py
pordego_dependency/analysis_result.py
pordego_dependency/analyzer.py
pordego_dependency/dependency_analysis.py
pordego_dependency/dependency_config.py
pordego_dependency/dependency_tools.py
pordego_dependency/entry_point.py
pordego_dependency/requirement_resolver.py
pordego_dependency/requirements_analysis.py
pordego_dependency/snakefood_lib.py
pordego_dependency-1.2.2.dist-info/DESCRIPTION.rst
pordego_dependency-1.2.2.dist-info/METADATA
pordego_dependency-1.2.2.dist-info/RECORD
pordego_dependency-1.2.2.dist-info/WHEEL
pordego_dependency-1.2.2.dist-info/entry_points.txt
pordego_dependency-1.2.2.dist-info/metadata.json
pordego_dependency-1.2.2.dist-info/top_level.txt
