Metadata-Version: 2.0
Name: pordego-dependency
Version: 1.2.2
Summary: Pordego plugin for code complexity analysis using the snakefood library
Home-page: https://github.com/ttreptow/pordego-dependency
Author: Tim Treptow
Author-email: tim.treptow@gmail.com
License: GNU GENERAL PUBLIC LICENSE
Requires-Dist: snakefood
Requires-Dist: requests
